{
	"credit": "Made with Blockbench",
	"ambientocclusion": false,
	"render_type": "cutout",
	"textures": {
		"0": "cerulean_vines:block/dawnberry_vine_stage_4",
		"1": "cerulean_vines:block/dawnberry_vine_stage_3",
		"particle": "cerulean_vines:block/dawnberry_vine_stage_3"
	},
	"elements": [
		{
			"from": [0, 0, 0],
			"to": [16, 16, 0],
			"faces": {
				"north": {"uv": [0, 16, 16, 0], "rotation": 180, "texture": "#1"},
				"east": {"uv": [0, 0, 16, 16], "rotation": 270, "texture": "#1"},
				"south": {"uv": [0, 0, 16, 16], "texture": "#1"},
				"west": {"uv": [0, 0, 16, 16], "rotation": 90, "texture": "#1"},
				"up": {"uv": [0, 0, 16, 16], "rotation": 180, "texture": "#1"},
				"down": {"uv": [0, 0, 16, 16], "texture": "#1"}
			}
		},
		{
			"from": [0, -2.70025, 4.41102],
			"to": [16, 13.29975, 4.41102],
			"rotation": {"angle": -45, "axis": "x", "origin": [8, 5.64975, 8.06102]},
			"faces": {
				"north": {"uv": [0, 16, 16, 0], "texture": "#0"},
				"east": {"uv": [0, 16, 16, 0], "texture": "#0"},
				"south": {"uv": [0, 16, 16, 0], "texture": "#0"},
				"west": {"uv": [0, 16, 16, 0], "texture": "#0"},
				"up": {"uv": [0, 16, 16, 0], "rotation": 180, "texture": "#0"},
				"down": {"uv": [0, 16, 16, 0], "rotation": 180, "texture": "#0"}
			}
		},
		{
			"from": [0, 12.29975, 3.41102],
			"to": [16, 12.29975, 19.41102],
			"rotation": {"angle": -45, "axis": "x", "origin": [8, 5.64975, 8.06102]},
			"faces": {
				"north": {"uv": [0, 16, 16, 0], "texture": "#0"},
				"east": {"uv": [0, 16, 16, 0], "rotation": 90, "texture": "#0"},
				"south": {"uv": [0, 16, 16, 0], "rotation": 180, "texture": "#0"},
				"west": {"uv": [0, 16, 16, 0], "rotation": 270, "texture": "#0"},
				"up": {"uv": [0, 16, 16, 0], "texture": "#0"},
				"down": {"uv": [0, 16, 16, 0], "rotation": 180, "texture": "#0"}
			}
		}
	]
}